rwrlock/__init__.py
rwrlock.egg-info/PKG-INFO
rwrlock.egg-info/SOURCES.txt
rwrlock.egg-info/dependency_links.txt
rwrlock.egg-info/top_level.txt
tests/__init__.py
tests/test_rwlock.py
rwrlock-0.0.5.dist-info/LICENSE
rwrlock-0.0.5.dist-info/METADATA
rwrlock-0.0.5.dist-info/WHEEL
rwrlock-0.0.5.dist-info/top_level.txt
rwrlock-0.0.5.dist-info/RECORD
