Metadata-Version: 2.1
Name: rwrlock
Version: 0.0.5
Summary: A limited re-entrant readwrite lock
Home-page: https://github.com/Mikemoore63/rwrlock
Author: Mike Moore
Author-email: z_z_zebra@yahoo.com
License: UNKNOWN
Platform: UNKNOWN
Classifier: Programming Language :: Python :: 3
Classifier: License :: OSI Approved :: MIT License
Classifier: Operating System :: OS Independent
License-File: LICENSE
